injector/__init__.py
injector/py.typed
injector-0.21.0.dist-info/COPYING
injector-0.21.0.dist-info/METADATA
injector-0.21.0.dist-info/WHEEL
injector-0.21.0.dist-info/top_level.txt
injector-0.21.0.dist-info/RECORD
