Metadata-Version: 2.1
Name: injector
Version: 0.21.0
Summary: Injector - Python dependency injection framework, inspired by Guice
Home-page: https://github.com/alecthomas/injector
Download-URL: https://pypi.org/project/injector/
Author: Alec Thomas
Author-email: alec@swapoff.org
License: BSD
Keywords: Dependency Injection,DI,Dependency Injection framework,Inversion of Control,IoC,Inversion of Control container
Platform: any
Provides-Extra: dev
License-File: COPYING
